xac/__init__.py
xac/__main__.py
xac/api/__init__.py
xac/api/auth/__init__.py
xac/api/auth/auth.py
xac/api/config.py
xac/api/config_file.py
xac/api/info.py
xac/api/resources/__init__.py
xac/api/resources/job.py
xac/api/resources/session.py
xac/api/resources/upload.py
xac/api/resources/usage.py
xac/api/schema/specs-schema.yaml
xac/main.py
xac/qexplain/__init__.py
xac/qexplain/explainer.py
xac/qexplain/transformers.py
xac/utils/__init__.py
xac/utils/config_utils.py
xac/utils/file_utils.py
xac/utils/helpers.py
xac/utils/logger.py
xac/utils/yaml_loader.py
xac-0.3.0.dist-info/entry_points.txt
xac-0.3.0.dist-info/WHEEL
xac-0.3.0.dist-info/METADATA
xac-0.3.0.dist-info/RECORD
