Metadata-Version: 2.1
Name: xac
Version: 0.3.0
Summary: Client for Xaipient Explainability REST API
Home-page: https://github.com/xaipient/xac
License: MIT
Author: Xaipient Team
Author-email: team@xaipient.com
Requires-Python: >=3.6.1,<4.0.0
Classifier: Development Status :: 3 - Alpha
Classifier: License :: OSI Approved :: MIT License
Classifier: Programming Language :: Python :: 3
Classifier: Programming Language :: Python :: 3.6
Classifier: Programming Language :: Python :: 3.7
Classifier: Programming Language :: Python :: 3.8
Classifier: Programming Language :: Python :: 3.9
Requires-Dist: alive-progress (>=1.6.1,<2.0.0)
Requires-Dist: dynaconf (>=3.1.1,<4.0.0)
Requires-Dist: halo (>=0.0.30,<0.0.31)
Requires-Dist: httpx (>=0.15.5,<0.16.0)
Requires-Dist: humanize (>=3.0.0,<4.0.0)
Requires-Dist: munch (>=2.5.0,<3.0.0)
Requires-Dist: pandas (>=1.1.3,<2.0.0)
Requires-Dist: pygments (>=2.7.1,<3.0.0)
Requires-Dist: safer (>=4.1.2,<5.0.0)
Requires-Dist: smart_open[all] (>=2.2.1,<3.0.0)
Requires-Dist: tabulate (>=0.8.7,<0.9.0)
Requires-Dist: typer[all] (>=0.3.2,<0.4.0)
Requires-Dist: yamale (>=3.0.4,<4.0.0)
Requires-Dist: yarl (>=1.6.0,<2.0.0)
Project-URL: Changelog, https://github.com/xaipient/xac/releases
Project-URL: Documentation, https://xaipient.github.io/xaipient-docs/
Project-URL: Repository, https://github.com/xaipient/xac
